wsgimagic/__init__.py
wsgimagic/aws_lambda.py
wsgimagic/magic_core.py
wsgimagic-1.0.0.dist-info/METADATA
wsgimagic-1.0.0.dist-info/RECORD
wsgimagic-1.0.0.dist-info/WHEEL
wsgimagic-1.0.0.dist-info/top_level.txt
