Metadata-Version: 2.1
Name: wsgimagic
Version: 1.0.0
Summary: Serverless WSGI apps made easy
Home-page: UNKNOWN
Author: Kyle Hinton
License: MIT
Platform: UNKNOWN
